demos/__init__.py
demos/build_demo.py
demos/build_demo_exec.py
demos/concur_demo.py
demos/configer_demo.py
demos/coordinator_demo.py
demos/ctpgateway_demo.py
demos/feeder_demo.py
demos/logger_demo.py
demos/process_manager_demo.py
demos/simple_engine.py
demos/demoproj/__init__.py
demos/demoproj/clear.py
demos/demoproj/except_file.py
demos/demoproj/main.py
demos/demoproj/test.py
logixbase/__init__.py
logixbase/algolib/__init__.py
logixbase/algolib/basestat.py
logixbase/algolib/chart.py
logixbase/algolib/fin.py
logixbase/algolib/matops.py
logixbase/algolib/optimization.py
logixbase/algolib/regression.py
logixbase/algolib/stattest.py
logixbase/algolib/stochastic.py
logixbase/algolib/timeseries.py
logixbase/algolib/utils.py
logixbase/compiler/__init__.py
logixbase/compiler/build.py
logixbase/compiler/schema.py
logixbase/configer/__init__.py
logixbase/configer/hotreloader.py
logixbase/configer/loader.py
logixbase/configer/proxy.py
logixbase/configer/schema.py
logixbase/engine/__init__.py
logixbase/engine/base.py
logixbase/engine/constant.py
logixbase/engine/manager.py
logixbase/engine/schema.py
logixbase/executor/__init__.py
logixbase/executor/base.py
logixbase/executor/context.py
logixbase/executor/coordinator.py
logixbase/executor/main.py
logixbase/executor/payload.py
logixbase/executor/process.py
logixbase/executor/schema.py
logixbase/executor/task.py
logixbase/executor/thread.py
logixbase/feeder/__init__.py
logixbase/feeder/base.py
logixbase/feeder/schema.py
logixbase/feeder/sqlfeeder.py
logixbase/feeder/tqfeeder.py
logixbase/feeder/tsfeeder.py
logixbase/feeder/wfeeder.py
logixbase/gateway/__init__.py
logixbase/gateway/base.py
logixbase/gateway/ctp.py
logixbase/gateway/schema.py
logixbase/gateway/api/__init__.py
logixbase/logger/__init__.py
logixbase/logger/constant.py
logixbase/logger/core.py
logixbase/logger/decorator.py
logixbase/logger/formatter.py
logixbase/logger/mpwriter.py
logixbase/logger/parser.py
logixbase/logger/schema.py
logixbase/logger/utils.py
logixbase-0.2.8.dist-info/LICENSE
logixbase-0.2.8.dist-info/METADATA
logixbase-0.2.8.dist-info/WHEEL
logixbase-0.2.8.dist-info/top_level.txt
logixbase-0.2.8.dist-info/RECORD
