Metadata-Version: 2.1
Name: logixbase
Version: 0.2.8
Summary: 高度模块化的量化交易策略开发框架
Home-page: https://github.com/339640170/logixbase
Author: LogixBase开发团队
Author-email: trader@logixquant.com
License: UNKNOWN
Platform: UNKNOWN
Classifier: Development Status :: 4 - Beta
Classifier: Intended Audience :: Financial and Insurance Industry
Classifier: Intended Audience :: Developers
Classifier: License :: OSI Approved :: MIT License
Classifier: Programming Language :: Python :: 3
Classifier: Programming Language :: Python :: 3.9
Classifier: Programming Language :: Python :: 3.10
Classifier: Programming Language :: Python :: 3.11
Classifier: Operating System :: OS Independent
Classifier: Topic :: Office/Business :: Financial :: Investment
Classifier: Topic :: Software Development :: Libraries :: Python Modules
Requires-Python: >=3.9
Requires-Dist: numpy>=1.20.0
Requires-Dist: pandas>=1.3.0
Requires-Dist: pyyaml>=6.0
Requires-Dist: pytz>=2022.1
Requires-Dist: requests>=2.27.0
Requires-Dist: sqlalchemy>=1.4.0
Requires-Dist: matplotlib>=3.5.0
Requires-Dist: numba>=0.55.0
Requires-Dist: statsmodels>=0.13.0
Requires-Dist: seaborn>=0.11.0
Requires-Dist: scikit-learn>=1.0.0
Requires-Dist: scipy>=1.7.0
Requires-Dist: cryptography==41.0.5
Requires-Dist: bcrypt==4.1.1
Requires-Dist: Cython>=0.29.0
Requires-Dist: pydantic>=1.9.0
Requires-Dist: watchdog>=2.1.0
Requires-Dist: psutil>=5.8.0
Requires-Dist: tqsdk>=1.9.0
Requires-Dist: path>=16.4.0
Requires-Dist: cx-Oracle>=8.0.0
Requires-Dist: pymssql>=2.2.0
Requires-Dist: uvicorn>=0.17.0
Requires-Dist: fastapi>=0.70.0
Requires-Dist: pandas-market-calendars>=4.0.0
Requires-Dist: paramiko>=2.10.0
Provides-Extra: dev
Requires-Dist: pytest>=7.0.0; extra == "dev"
Requires-Dist: pytest-cov>=3.0.0; extra == "dev"
Requires-Dist: black>=22.1.0; extra == "dev"
Requires-Dist: flake8>=4.0.0; extra == "dev"
Requires-Dist: mypy>=0.931; extra == "dev"
Requires-Dist: sphinx>=4.4.0; extra == "dev"
Requires-Dist: build>=0.8.0; extra == "dev"
Requires-Dist: twine>=4.0.0; extra == "dev"
